xwl/__init__.py
xwl/dispatcher.py
xwl/example.py.test
xwl/py.typed
xwl/wsgi.py
xwl/wsgi.py.test
xwl/xwl.js
xwl/xwl.py.test
xwl/example/1.svg.gz
xwl/example/app.py
xwl/example/mt-server.py
xwl/example/server.py
xwl/example/submodule.py
xwl/example/test.html
xwl/example/test.js
xwl/example/test2.html
xwl/example/test2.js
xwl/example/xwl.js
xwl-1.0.2.dist-info/METADATA
xwl-1.0.2.dist-info/WHEEL
xwl-1.0.2.dist-info/top_level.txt
xwl-1.0.2.dist-info/RECORD
